Workbook

Sheet Tablero Compra
J2: Aceitera de Soja | O2: Desarrollado por Simpleza S.A.
J3: Tablero de Sensibilidad del Negocio.
B7: Condiciones Venta
K8: Margen de Ventas | N8: =Molienda!O46 -> 11.676746 | P8: =Molienda!P46 -> 91.078616
C9: Precio de Venta Aceite de Soja | E9: =Molienda!E10 -> 620 | F9: u$s/Tn | G9: =Molienda!G10 -> 4836 | H9: $/Tn
C11: Precio de Venta Expeller de Soja 6%MG | E11: =Molienda!E12 -> 334 | F11: u$s/Tn | G11: =Molienda!G12 -> 2605.2 | H11: $/Tn
F12: 713
C14: Flete Venta Aceite | E14: =Molienda!E26 -> 0 | G14: =Molienda!G26 -> 0 | H14: Costo P.G. | K14: Precio Indiferencia Poroto de Soja | N14: =Molienda!O43 -> 314.67675 | P14: =Molienda!P43 -> 2454.4786
C15: Flete Venta Expeller | E15: =Molienda!E27 -> 0 | F15: 0 | G15: =Molienda!G27 -> 0 | H15: Costo P.G.
B18: Condiciones Compra
C20: Precio de Compra Soja (A retirar Campo) | E20: =Molienda!E17 -> 303 | F20: u$s/Tn | G20: =Molienda!G17 -> 2363.4 | H20: $/Tn | K20: Precio Equivalente Puerto Rosario | N20: =Molienda!E49 -> 327.14103 | P20: =Molienda!F49 -> 2551.7
C23: Flete Campo a Planta Km | E23: =Molienda!E29 -> 0 | G23: =Molienda!G29 -> 0 | H23: Costo P.G.
C24: Flete Campo a Puerto Km | E24: =Molienda!E30 -> 445 | F24: 360 | G24: =Molienda!G30 -> 188.3 | H24: Calculo Eq.

Sheet Molienda
I3: Aceitera de Soja | P3: Desarrollado por Simpleza S.A.
I4: Tablero de Sensibilidad del Negocio.
B8: Variables relevantes
Q9: Insumos y Productos del Proceso
C10: Precio de Venta Aceite de Soja | E10: 620 | F10: u$s/Tn | G10: =E10*$E$20 -> 4836 | H10: $/Tn | J10: Proporción Aceite | L10: =M10/1000 -> 0.14 | M10: 140
C12: Precio de Venta Expellet de Soja 6%MG | E12: 334 | F12: u$s/Tn | G12: =E12*$E$20 -> 2605.2 | H12: $/Tn | J12: Proporción Harina de Soja | L12: =1-L10 -> 0.86
T13: =CONCATENATE(W13," ",ROUND(X13,0),"Tn") -> Poroto Soja 650Tn | W13: Poroto Soja | X13: =L20 -> 650
C14: Precio de Venta Harina de Soja | E14: 334 | F14: u$s/Tn | G14: =E14*$E$20 -> 2605.2 | H14: $/Tn | T14: =CONCATENATE(W14," ",ROUND(X14,0),"Tn") -> Mermas 25Tn | W14: Mermas | X14: =X13*E37 -> 25.418994
J15: Pellet de Soja 6% MG | L15: =M15/1000 -> 1 | M15: 1000 | T15: =CONCATENATE(W15," ",ROUND(X15,0),"Tn") -> Aceite 87Tn | W15: Aceite | X15: =(X13-X14)*L10 -> 87.441341
T16: =CONCATENATE(W16," ",ROUND(X16,0),"Tn") -> Harina 537Tn | W16: Harina | X16: =(X13-X14)*L12 -> 537.13966
C17: Precio de Compra Soja (A retirar Campo) | E17: 303 | F17: u$s/Tn | G17: =E17*$E$20 -> 2363.4 | H17: $/Tn | J17: Harina de Soja | L17: =1-L15 -> 0 | T17: =CONCATENATE(W17," ",ROUND(X17,0),"Tn") -> Pellet 6% 537Tn | W17: Pellet 6% | X17: =X16*L15 -> 537.13966
T18: =CONCATENATE(W18," ",ROUND(X18,0),"Tn") -> Harina 0Tn | W18: Harina | X18: =X16*L17 -> 0
C20: Tipo de Cambio | E20: 7.8 | F20: $/U$S | G20: 628 | J20: Molineda Poroto de Soja | L20: 650 | M20: Tn/mes
C24: Costo de Secada 14 a 10.5ᴼ | E24: =G24/E20 -> 1.6666667 | F24: u$s/Tn | G24: 13 | H24: $/Tn | J24: Molienda 23 a 18 hs | L24: =L20*N24/100 -> 650 | M24: Tn/mes | N24: 100
J25: Molienda 18 a 23 hs | L25: =L20-L24 -> 0
C26: Flete Venta Aceite | E26: 0 | G26: =SUMPRODUCT((E26='Flete y Mermas'!A2:A1001)*('Flete y Mermas'!B2:B1001)) -> 0 | J26: Multa (Molienda Hora Pico) | L26: =IF(L25>0,P82*O82,0)/E20 -> 0 | M26: U$S/Mes
C27: Flete Venta Expeler | E27: 0 | F27: 0 | G27: =SUMPRODUCT((E27='Flete y Mermas'!A2:A1001)*('Flete y Mermas'!B2:B1001)) -> 0 | O27: Aceite | P27: =L10*(1-E37) -> 0.13452514
J28: Coberturas MAT | L28: 0 | M28: Tn/mes
C29: Flete Campo a Planta Km | E29: 0 | G29: =SUMPRODUCT((E29='Flete y Mermas'!A2:A1001)*('Flete y Mermas'!B2:B1001)) -> 0
C30: Flete Campo a Puerto Km | E30: 445 | F30: 0 | G30: =SUMPRODUCT((E30='Flete y Mermas'!A2:A1001)*('Flete y Mermas'!B2:B1001)) -> 188.3 | J30: Costo Cobertura U$S/Tn | L30: =M30/10 -> 0 | M30: 0
O31: Pellet | P31: =L12*(1-E37)*L15 -> 0.82636872
C32: Comisiones de Compra Soja | E32: =F32/1000 -> 0 | F32: 0 | O32: Mermas | P32: =E37 -> 0.039106145
C33: Comisiones de Venta Aceite | E33: =F33/1000 -> 0.005 | F33: 5
C34: Comisiones de Venta Pellet | E34: =F34/1000 -> 0.005 | F34: 5
C37: Ineficiencia total Mermas del Proceso | E37: =SUM(K37,K38,P37,P38) -> 0.039106145 | F37: Mermar sobre poroto de soja ingresado | H37: Mermas Humedad 14 a 10,5 | K37: =(14-10.5)/(100-10.5) -> 0.039106145 | L37: 0 | N37: Mermas Acondicionado | P37: =Q37/1000 -> 0 | Q37: 0
H38: Mermas Descascarado | K38: =L38/1000 -> 0 | L38: 0 | N38: Mermas Estruzado | P38: =Q38/1000 -> 0 | Q38: 0
B41: Indicadores del Negocio
C43: Margen de Ventas | E43: =E89/E56 -> 0.032488402 | G43: Precio Indiferencia Aceite | I43: =F60+F76-F58 -> 533.20027 | K43: =I43*$E$20 -> 4158.9621 | L43: =I43/E10-1 -> -0.13999956 | M43: Precio Indiferencia Poroto | O43: =E56-SUM(E62:E75,E76) -> 314.67675 | P43: =O43*$E$20 -> 2454.4786 | Q43: =O43/E14-1 -> -0.057854055
C46: Molienda Indiferencia | E46: =H76/(E56-E60) -> 502.05587 | G46: Precio Indiferencia Pellet | J46: =G60+G76-G57 -> 319.86981 | K46: =J46*$E$20 -> 2494.9845 | L46: =J46/(E12*L15+E14*L17)-1 -> -0.042305953 | M46: Margen de Ventas | O46: =E89 -> 11.676746 | P46: =O46*$E$20 -> 91.078616
C49: Precio de Soja Pizarra Rosario | E49: =F49/E20 -> 327.14103 | F49: =G17+G30 -> 2551.7
E55: U$S/Tn Poroto Soja | F55: U$S/Tn Aceite Soja | G55: U$S/Tn Harina Soja | H55: U$S/Mes | J55: $/Tn Poroto Soja | K55: $/Tn Aceite Soja | L55: $/Tn Harina Soja | M55: $/Mes | O55: Unidades | P55: $/Unidad
B56: Ingresos por Ventas | E56: =H56/$L$20 -> 359.41274 | F56: =H56/($L$20*(1-$E$37)*$L$10) -> 2671.7143 | G56: =H56/($L$20*(1-$E$37)*$L$12) -> 434.93023 | H56: =SUM(H57:H59) -> 233618.28 | J56: =E56*$E$20 -> 2803.4194 | K56: =F56*$E$20 -> 20839.371 | L56: =G56*$E$20 -> 3392.4558 | M56: =H56*$E$20 -> 1822222.6
B57: * | C57: Aceite de Soja | E57: =H57/$L$20 -> 83.405587 | F57: =H57/($L$20*(1-$E$37)*$L$10) -> 620 | G57: =H57/($L$20*(1-$E$37)*$L$12) -> 100.93023 | H57: =$L$20*(1-$E$37)*L10*E10 -> 54213.631 | J57: =E57*$E$20 -> 650.56358 | K57: =F57*$E$20 -> 4836 | L57: =G57*$E$20 -> 787.25581 | M57: =H57*$E$20 -> 422866.32
B58: * | C58: Pellet de Soja | E58: =H58/$L$20 -> 276.00715 | F58: =H58/($L$20*(1-$E$37)*$L$10) -> 2051.7143 | G58: =H58/($L$20*(1-$E$37)*$L$12) -> 334 | H58: =$L$20*(1-$E$37)*L12*E12 -> 179404.65 | J58: =E58*$E$20 -> 2152.8558 | K58: =F58*$E$20 -> 16003.371 | L58: =G58*$E$20 -> 2605.2 | M58: =H58*$E$20 -> 1399356.3
B59: * | C59: Harina de Soja | E59: =H59/$L$20 -> 0 | F59: =H59/($L$20*(1-$E$37)*$L$10) -> 0 | G59: =H59/($L$20*(1-$E$37)*$L$12) -> 0 | H59: =$L$20*(1-$E$37)*L12*E14*L17 -> 0 | J59: =E59*$E$20 -> 0 | K59: =F59*$E$20 -> 0 | L59: =G59*$E$20 -> 0 | M59: =H59*$E$20 -> 0
B60: Costos Variables | E60: =H60/$L$20 -> 308.11037 | F60: =H60/($L$20*(1-$E$37)*$L$10) -> 2290.3553 | G60: =H60/($L$20*(1-$E$37)*$L$12) -> 372.84854 | H60: =SUM(H61:H75) -> 200271.74 | J60: =E60*$E$20 -> 2403.2609 | K60: =F60*$E$20 -> 17864.771 | L60: =G60*$E$20 -> 2908.2186 | M60: =H60*$E$20 -> 1562119.6
B61: * | C61: Poroto de Soja | E61: =H61/$L$20 -> 303 | F61: =H61/($L$20*(1-$E$37)*$L$10) -> 2252.3671 | G61: =H61/($L$20*(1-$E$37)*$L$12) -> 366.66441 | H61: =E17*L20 -> 196950 | J61: =E61*$E$20 -> 2363.4 | K61: =F61*$E$20 -> 17568.463 | L61: =G61*$E$20 -> 2859.9824 | M61: =H61*$E$20 -> 1536210
B62: * | C62: Comisión de Compra | E62: =H62/$L$20 -> 0 | F62: =H62/($L$20*(1-$E$37)*$L$10) -> 0 | G62: =H62/($L$20*(1-$E$37)*$L$12) -> 0 | H62: =O62*P62 -> 0 | J62: =E62*$E$20 -> 0 | K62: =F62*$E$20 -> 0 | L62: =G62*$E$20 -> 0 | M62: =H62*$E$20 -> 0 | O62: =H61 -> 196950 | P62: =E32 -> 0
B63: * | C63: Comisión de Venta Aceite | E63: =H63/$L$20 -> 0.41702793 | F63: =H63/($L$20*(1-$E$37)*$L$10) -> 3.1 | G63: =H63/($L$20*(1-$E$37)*$L$12) -> 0.50465116 | H63: =O63*P63 -> 271.06816 | J63: =E63*$E$20 -> 3.2528179 | K63: =F63*$E$20 -> 24.18 | L63: =G63*$E$20 -> 3.9362791 | M63: =H63*$E$20 -> 2114.3316 | O63: =H57 -> 54213.631 | P63: =E33 -> 0.005
B64: * | C64: Comisión de Venta Harina | E64: =H64/$L$20 -> 1.3800358 | F64: =H64/($L$20*(1-$E$37)*$L$10) -> 10.258571 | G64: =H64/($L$20*(1-$E$37)*$L$12) -> 1.67 | H64: =O64*P64 -> 897.02324 | J64: =E64*$E$20 -> 10.764279 | K64: =F64*$E$20 -> 80.016857 | L64: =G64*$E$20 -> 13.026 | M64: =H64*$E$20 -> 6996.7813 | O64: =H58 -> 179404.65 | P64: =E34 -> 0.005
B65: * | C65: Flete Campo a Planta | E65: =H65/$L$20 -> 0 | F65: =H65/($L$20*(1-$E$37)*$L$10) -> 0 | G65: =H65/($L$20*(1-$E$37)*$L$12) -> 0 | H65: =O65*P65/$E$20 -> 0 | J65: =E65*$E$20 -> 0 | K65: =F65*$E$20 -> 0 | L65: =G65*$E$20 -> 0 | M65: =H65*$E$20 -> 0 | O65: =L20 -> 650 | P65: =G29 -> 0
B66: * | C66: Flete Venta Expelet | E66: =H66/$L$20 -> 0 | F66: =H66/($L$20*(1-$E$37)*$L$10) -> 0 | G66: =H66/($L$20*(1-$E$37)*$L$12) -> 0 | H66: =M66/$E$20 -> 0 | J66: =E66*$E$20 -> 0 | K66: =F66*$E$20 -> 0 | L66: =G66*$E$20 -> 0 | M66: =L20*L10*G26*(1-E37) -> 0
B67: * | C67: Flete Venta Aceite | E67: =H67/$L$20 -> 0 | F67: =H67/($L$20*(1-$E$37)*$L$10) -> 0 | G67: =H67/($L$20*(1-$E$37)*$L$12) -> 0 | H67: =M67/$E$20 -> 0 | J67: =E67*$E$20 -> 0 | K67: =F67*$E$20 -> 0 | L67: =G67*$E$20 -> 0 | M67: =L20*L12*G27*(1-E37) -> 0
B68: * | C68: Secada 14 a 10,5 | E68: =H68/$L$20 -> 1.6666667 | F68: =H68/($L$20*(1-$E$37)*$L$10) -> 12.389258 | G68: =H68/($L$20*(1-$E$37)*$L$12) -> 2.016856 | H68: =O68*P68/$E$20 -> 1083.3333 | J68: =E68*$E$20 -> 13 | K68: =F68*$E$20 -> 96.636213 | L68: =G68*$E$20 -> 15.731476 | M68: =H68*$E$20 -> 8450 | O68: =L20 -> 650 | P68: =G24 -> 13
B69: * | C69: Cobertura de Precios | E69: =H69/$L$20 -> 0 | F69: =H69/($L$20*(1-$E$37)*$L$10) -> 0 | G69: =H69/($L$20*(1-$E$37)*$L$12) -> 0 | H69: =O69*P69/$E$20 -> 0 | J69: =E69*$E$20 -> 0 | K69: =F69*$E$20 -> 0 | L69: =G69*$E$20 -> 0 | M69: =H69*$E$20 -> 0 | O69: =L28 -> 0 | P69: =L30*E20 -> 0
B70: * | C70: IIBB | E70: =H70/$L$20 -> 0 | F70: =H70/($L$20*(1-$E$37)*$L$10) -> 0 | G70: =H70/($L$20*(1-$E$37)*$L$12) -> 0 | H70: =H56*O70 -> 0 | J70: =E70*$E$20 -> 0 | K70: =F70*$E$20 -> 0 | L70: =G70*$E$20 -> 0 | M70: =H70*$E$20 -> 0
B71: * | C71: ITF | E71: =H71/$L$20 -> 0 | F71: =H71/($L$20*(1-$E$37)*$L$10) -> 0 | G71: =H71/($L$20*(1-$E$37)*$L$12) -> 0 | H71: =H56*O71 -> 0 | J71: =E71*$E$20 -> 0 | K71: =F71*$E$20 -> 0 | L71: =G71*$E$20 -> 0 | M71: =H71*$E$20 -> 0
B72: * | C72: Energia Electrica (No Pico) | E72: =H72/$L$20 -> 1.5483462 | F72: =H72/($L$20*(1-$E$37)*$L$10) -> 11.509716 | G72: =H72/($L$20*(1-$E$37)*$L$12) -> 1.8736747 | H72: =O72*P72/$E$20 -> 1006.425 | J72: =E72*$E$20 -> 12.0771 | K72: =F72*$E$20 -> 89.775785 | L72: =G72*$E$20 -> 14.614663 | M72: =H72*$E$20 -> 7850.115 | O72: =57.51*L24 -> 37381.5 | P72: 0.21
B73: * | C73: Energia Electrica (Pico) | E73: =H73/$L$20 -> 0 | F73: =H73/($L$20*(1-$E$37)*$L$10) -> 0 | G73: =H73/($L$20*(1-$E$37)*$L$12) -> 0 | H73: =O73*P73/$E$20 -> 0 | J73: =E73*$E$20 -> 0 | K73: =F73*$E$20 -> 0 | L73: =G73*$E$20 -> 0 | M73: =H73*$E$20 -> 0 | O73: =57.51*L25 -> 0 | P73: 0.35
B74: * | C74: Mantenimiento Linea 1 | E74: =H74/$L$20 -> 0.098290598 | F74: =H74/($L$20*(1-$E$37)*$L$10) -> 0.73064855 | G74: =H74/($L$20*(1-$E$37)*$L$12) -> 0.11894279 | H74: =O74*P74/$E$20 -> 63.888889 | J74: =E74*$E$20 -> 0.76666667 | K74: =F74*$E$20 -> 5.6990587 | L74: =G74*$E$20 -> 0.92775374 | M74: =H74*$E$20 -> 498.33333 | O74: =MIN(L24,750)/1.5 -> 433.33333 | P74: =1*1.15 -> 1.15
B75: * | C75: Mantenimiento Linea 2 | E75: =H75/$L$20 -> 0 | F75: =H75/($L$20*(1-$E$37)*$L$10) -> 0 | G75: =H75/($L$20*(1-$E$37)*$L$12) -> 0 | H75: =O75*P75/$E$20 -> 0 | J75: =E75*$E$20 -> 0 | K75: =F75*$E$20 -> 0 | L75: =G75*$E$20 -> 0 | M75: =H75*$E$20 -> 0 | O75: =MAX(0,((L20-(O74*1.5))/1.5)) -> 0 | P75: =0.6*1.15 -> 0.69
B76: Costos Fijos | E76: =H76/$L$20 -> 39.625625 | F76: =H76/($L$20*(1-$E$37)*$L$10) -> 294.55925 | G76: =H76/($L$20*(1-$E$37)*$L$12) -> 47.951506 | H76: =SUM(H77:H88) -> 25756.656 | J76: =E76*$E$20 -> 309.07987 | K76: =F76*$E$20 -> 2297.5622 | L76: =G76*$E$20 -> 374.02175 | M76: =H76*$E$20 -> 200901.92
B77: * | C77: Personal Planta | E77: =H77/$L$20 -> 6.171458 | F77: =H77/($L$20*(1-$E$37)*$L$10) -> 45.875871 | G77: =H77/($L$20*(1-$E$37)*$L$12) -> 7.4681651 | H77: =O77*P77/$E$20 -> 4011.4477 | J77: =E77*$E$20 -> 48.137372 | K77: =F77*$E$20 -> 357.8318 | L77: =G77*$E$20 -> 58.251688 | M77: =H77*$E$20 -> 31289.292 | O77: 4 | P77: =(3816*1.55)*1.15*1.15 -> 7822.323
B78: * | C78: Personal Administrativo | E78: =H78/$L$20 -> 1.4007544 | F78: =H78/($L$20*(1-$E$37)*$L$10) -> 10.412585 | G78: =H78/($L$20*(1-$E$37)*$L$12) -> 1.695072 | H78: =O78*P78/$E$20 -> 910.49038 | J78: =E78*$E$20 -> 10.925885 | K78: =F78*$E$20 -> 81.218162 | L78: =G78*$E$20 -> 13.221561 | M78: =H78*$E$20 -> 7101.825 | O78: 1 | P78: =(4000+600+770)*1.15*1.15 -> 7101.825
B79: * | C79: Cargas Sociales | E79: =H79/$L$20 -> 2.7613412 | F79: =H79/($L$20*(1-$E$37)*$L$10) -> 20.526581 | G79: =H79/($L$20*(1-$E$37)*$L$12) -> 3.3415365 | H79: =O79*P79/$E$20 -> 1794.8718 | J79: =E79*$E$20 -> 21.538462 | K79: =F79*$E$20 -> 160.10733 | L79: =G79*$E$20 -> 26.063985 | M79: =H79*$E$20 -> 14000 | O79: 1 | P79: 14000
B80: * | C80: Energia (Potencia Fuera Pico) | E80: =H80/$L$20 -> 1.8224852 | F80: =H80/($L$20*(1-$E$37)*$L$10) -> 13.547544 | G80: =H80/($L$20*(1-$E$37)*$L$12) -> 2.2054141 | H80: =P80*O80/$E$20 -> 1184.6154 | J80: =E80*$E$20 -> 14.215385 | K80: =F80*$E$20 -> 105.67084 | L80: =G80*$E$20 -> 17.20223 | M80: =H80*$E$20 -> 9240 | O80: 330 | P80: 28
B81: * | C81: Energia (Potencia Pico) | E81: =H81/$L$20 -> 2.8106509 | F81: =H81/($L$20*(1-$E$37)*$L$10) -> 20.893127 | G81: =H81/($L$20*(1-$E$37)*$L$12) -> 3.4012068 | H81: =P81*O81/$E$20 -> 1826.9231 | J81: =E81*$E$20 -> 21.923077 | K81: =F81*$E$20 -> 162.96639 | L81: =G81*$E$20 -> 26.529413 | M81: =H81*$E$20 -> 14250 | O81: 15 | P81: 950
B82: * | C82: Energia (Exceso Potencia) | E82: =H82/$L$20 -> 0 | F82: =H82/($L$20*(1-$E$37)*$L$10) -> 0 | G82: =H82/($L$20*(1-$E$37)*$L$12) -> 0 | H82: =L26 -> 0 | J82: =E82*$E$20 -> 0 | K82: =F82*$E$20 -> 0 | L82: =G82*$E$20 -> 0 | M82: =H82*$E$20 -> 0 | O82: =O80-O81 -> 315 | P82: 70
B83: * | C83: Gasto de Vehiculos | E83: =H83/$L$20 -> 0.69033531 | F83: =H83/($L$20*(1-$E$37)*$L$10) -> 5.1316453 | G83: =H83/($L$20*(1-$E$37)*$L$12) -> 0.83538412 | H83: =O83*P83/$E$20 -> 448.71795 | J83: =E83*$E$20 -> 5.3846154 | K83: =F83*$E$20 -> 40.026834 | L83: =G83*$E$20 -> 6.5159962 | M83: =H83*$E$20 -> 3500 | O83: 1 | P83: 3500
B84: * | C84: Gastos Admin. Y Estructura | E84: =H84/$L$20 -> 2.3668639 | F84: =H84/($L$20*(1-$E$37)*$L$10) -> 17.594213 | G84: =H84/($L$20*(1-$E$37)*$L$12) -> 2.8641741 | H84: =O84*P84/$E$20 -> 1538.4615 | J84: =E84*$E$20 -> 18.461538 | K84: =F84*$E$20 -> 137.23486 | L84: =G84*$E$20 -> 22.340558 | M84: =H84*$E$20 -> 12000 | O84: 1 | P84: 12000
B85: * | C85: Mantenimientos Fijos | E85: =H85/$L$20 -> 1.9723866 | F85: =H85/($L$20*(1-$E$37)*$L$10) -> 14.661844 | G85: =H85/($L$20*(1-$E$37)*$L$12) -> 2.3868118 | H85: =O85*P85/$E$20 -> 1282.0513 | J85: =E85*$E$20 -> 15.384615 | K85: =F85*$E$20 -> 114.36238 | L85: =G85*$E$20 -> 18.617132 | M85: =H85*$E$20 -> 10000 | O85: 1 | P85: 10000
B86: * | C86: Otros gastos | E86: =H86/$L$20 -> 2.9585799 | F86: =H86/($L$20*(1-$E$37)*$L$10) -> 21.992766 | G86: =H86/($L$20*(1-$E$37)*$L$12) -> 3.5802177 | H86: =O86*P86/$E$20 -> 1923.0769 | J86: =E86*$E$20 -> 23.076923 | K86: =F86*$E$20 -> 171.54357 | L86: =G86*$E$20 -> 27.925698 | M86: =H86*$E$20 -> 15000 | O86: 1 | P86: 15000
B87: * | C87: Alquileres | E87: =H87/$L$20 -> 0 | F87: =H87/($L$20*(1-$E$37)*$L$10) -> 0 | G87: =H87/($L$20*(1-$E$37)*$L$12) -> 0 | H87: =O87*P87/$E$20 -> 0 | J87: =E87*$E$20 -> 0 | K87: =F87*$E$20 -> 0 | L87: =G87*$E$20 -> 0 | M87: =H87*$E$20 -> 0
B88: * | C88: Amortizaciones | E88: =H88/$L$20 -> 16.670769 | F88: =H88/($L$20*(1-$E$37)*$L$10) -> 123.92308 | G88: =H88/($L$20*(1-$E$37)*$L$12) -> 20.173524 | H88: =O88/5/12 -> 10836 | J88: =E88*$E$20 -> 130.032 | K88: =F88*$E$20 -> 966.6 | L88: =G88*$E$20 -> 157.35349 | M88: =H88*$E$20 -> 84520.8 | O88: =1.2*541800 -> 650160
B89: Margen Negocio | E89: =E56-E60-E76 -> 11.676746 | F89: =F56-F60-F76 -> 86.799729 | G89: =G56-G60-G76 -> 14.130188 | H89: =H56-H60-H76 -> 7589.8847 | J89: =E89*$E$20 -> 91.078616 | K89: =F89*$E$20 -> 677.03789 | L89: =G89*$E$20 -> 110.21547 | M89: =H89*$E$20 -> 59201.101

Sheet Fazon
F2: Aceitera de Soja | H2: Desarrollado por Simpleza S.A.
F3: Tablero Fazon
B7: Soja Ingreso | C7: 1000 | D7: Kg
B10: Costo Molienda | C10: =Molienda!J76+SUM(Molienda!J68:J75) -> 334.92364 | D10: $/Tn Ingreso
B13: Efec. Proceso | C13: =1-Molienda!E37 -> 0.96089385
B14: Soja Molida | C14: =C7*C13 -> 960.89385 | D14: Kg
B17: Expeller | C17: =C14*Molienda!L12 -> 826.36872 | D17: Kg
B18: Aceite | C18: =Molienda!L10*Fazon!C14 -> 134.52514 | D18: Kg
C21: Retiro Dueño Soja | E21: Saldo Pampa Gringa | G21: Valor Neto
B22: Expeller | C22: 900 | D22: Kg | E22: =C17-C22 -> -73.631285 | F22: Kg | G22: =Molienda!G12*(1-Molienda!E34)-Molienda!G27 -> 2592.174 | H22: $/Kg
B23: Aceite | C23: 0 | D23: Kg | E23: =C18-C23 -> 134.52514 | F23: Kg | G23: =Molienda!G10*(1-Molienda!E33)-Molienda!G26 -> 4811.82 | H23: $/Kg
B25: Ingreso | C25: =SUMPRODUCT(E22:E23,G22:G23)/1000*C13 -> 438.59583 | D25: $/Tn Soja Ingresada
B26: Costo | C26: =C10 -> 334.92364 | D26: $/Tn Soja Ingresada
B28: Margen | C28: =C25-C26 -> 103.67219 | D28: $/Tn Soja Ingresada
C29: =C28/Molienda!E20 -> 13.291306 | D29: U$S/Tn Soja Ingresada
B40: 1

Sheet Instructivo
F3: Aceitera de Soja | J3: Desarrollado por Simpleza S.A.
F4: Tablero de Sensibilidad del Negocio.
B7: El objetivo de este tablero es realizar el calculo de resultados de moler soja
B8: y vender los subproductos.
B9: Teniendo en cuenta los costos de estructura dde Agroindustria Pampa
B11: Modo de uso
B13: En la hoja Molienda se podrán modificar las siguientes variables
B15: * Precio de venta de aceite de soja ($/tn) | F15: * Rendimiento de subproductos
B16: * Precio de venta de Expeller de soja ($/tn)
B17: * Precio de venta de hariana de soja ($/tn)
B18: * Precio de compra de Soja poroto ($/tn) - precio neto que cobra el cliente
B19: * Tipo de cambio
B21: * Costo de secada para clientes ($/tn)
B23: * Fletes a planta (de soja poroto)
B24: * Flete campo a puerto (es el dto a realzar al cliente)
B25: * Comisiones
B26: * Molienda de soja poroto

Sheet Flete y Mermas
B1: $/Km
A2: 1 | B2: 25.3
A3: 2 | B3: 25.3
A4: 3 | B4: 25.3
A5: 4 | B5: 25.3
A6: 5 | B6: 25.3
A7: 6 | B7: 25.3
A8: 7 | B8: 25.3
A9: 8 | B9: 25.3
A10: 9 | B10: 25.3
A11: 10 | B11: 25.3
A12: 11 | B12: 25.83
A13: 12 | B13: 26.35
... A1001: 1000 | B1001: 395

Sheet Coberturas
A3: Condciones a hoy
B4: Aceite usd 755 (o 735 + iva) comision 1% flete usd 25/tn
B5: Pellets 88% precio pizarra menos flete aprox. 8% comision 0,5%
B6: Compra de soja 91% precio pizarra menos $95/tn
A9: Fecha | B9: Tipo de cobertura | C9: Precio Ejercicio | D9: costo Prima | E9: Valor P mercado | F9: Diferencia
